{
  "formatVersion": 1,
  "database": {
    "version": 1,
    "identityHash": "9bae16bd8f5653c626ee4a064e4f7128",
    "entities": [
      {
        "tableName": "ledger_entries",
        "createSql": "CREATE TABLE IF NOT EXISTS `${TABLE_NAME}` (`id` INTEGER PRIMARY KEY AUTOINCREMENT NOT NULL, `type` TEXT NOT NULL, `name` TEXT NOT NULL, `principal` REAL NOT NULL, `interestType` TEXT NOT NULL, `period` TEXT, `compoundPeriod` TEXT NOT NULL, `rateRupees` REAL NOT NULL, `fromDate` INTEGER NOT NULL, `notes` TEXT, `isClosed` INTEGER NOT NULL, `createdAt` INTEGER NOT NULL, `updatedAt` INTEGER NOT NULL)",
        "fields": [
          {
            "fieldPath": "id",
            "columnName": "id",
            "affinity": "INTEGER",
            "notNull": true
          },
          {
            "fieldPath": "type",
            "columnName": "type",
            "affinity": "TEXT",
            "notNull": true
          },
          {
            "fieldPath": "name",
            "columnName": "name",
            "affinity": "TEXT",
            "notNull": true
          },
          {
            "fieldPath": "principal",
            "columnName": "principal",
            "affinity": "REAL",
            "notNull": true
          },
          {
            "fieldPath": "interestType",
            "columnName": "interestType",
            "affinity": "TEXT",
            "notNull": true
          },
          {
            "fieldPath": "period",
            "columnName": "period",
            "affinity": "TEXT",
            "notNull": false
          },
          {
            "fieldPath": "compoundPeriod",
            "columnName": "compoundPeriod",
            "affinity": "TEXT",
            "notNull": true
          },
          {
            "fieldPath": "rateRupees",
            "columnName": "rateRupees",
            "affinity": "REAL",
            "notNull": true
          },
          {
            "fieldPath": "fromDate",
            "columnName": "fromDate",
            "affinity": "INTEGER",
            "notNull": true
          },
          {
            "fieldPath": "notes",
            "columnName": "notes",
            "affinity": "TEXT",
            "notNull": false
          },
          {
            "fieldPath": "isClosed",
            "columnName": "isClosed",
            "affinity": "INTEGER",
            "notNull": true
          },
          {
            "fieldPath": "createdAt",
            "columnName": "createdAt",
            "affinity": "INTEGER",
            "notNull": true
          },
          {
            "fieldPath": "updatedAt",
            "columnName": "updatedAt",
            "affinity": "INTEGER",
            "notNull": true
          }
        ],
        "primaryKey": {
          "autoGenerate": true,
          "columnNames": [
            "id"
          ]
        },
        "indices": [],
        "foreignKeys": []
      },
      {
        "tableName": "ledger_payments",
        "createSql": "CREATE TABLE IF NOT EXISTS `${TABLE_NAME}` (`id` INTEGER PRIMARY KEY AUTOINCREMENT NOT NULL, `entryId` INTEGER NOT NULL, `amount` REAL NOT NULL, `date` INTEGER NOT NULL, `note` TEXT)",
        "fields": [
          {
            "fieldPath": "id",
            "columnName": "id",
            "affinity": "INTEGER",
            "notNull": true
          },
          {
            "fieldPath": "entryId",
            "columnName": "entryId",
            "affinity": "INTEGER",
            "notNull": true
          },
          {
            "fieldPath": "amount",
            "columnName": "amount",
            "affinity": "REAL",
            "notNull": true
          },
          {
            "fieldPath": "date",
            "columnName": "date",
            "affinity": "INTEGER",
            "notNull": true
          },
          {
            "fieldPath": "note",
            "columnName": "note",
            "affinity": "TEXT",
            "notNull": false
          }
        ],
        "primaryKey": {
          "autoGenerate": true,
          "columnNames": [
            "id"
          ]
        },
        "indices": [],
        "foreignKeys": []
      }
    ],
    "views": [],
    "setupQueries": [
      "CREATE TABLE IF NOT EXISTS room_master_table (id INTEGER PRIMARY KEY,identity_hash TEXT)",
      "INSERT OR REPLACE INTO room_master_table (id,identity_hash) VALUES(42, '9bae16bd8f5653c626ee4a064e4f7128')"
    ]
  }
}